odoo8_addon_sale_line_quantity_properties_based-8.0.1.0.0.99.dev18-py3.8-nspkg.pth
odoo_addons/sale_line_quantity_properties_based/README.rst
odoo_addons/sale_line_quantity_properties_based/__init__.py
odoo_addons/sale_line_quantity_properties_based/__openerp__.py
odoo_addons/sale_line_quantity_properties_based/product.py
odoo_addons/sale_line_quantity_properties_based/product_view.xml
odoo_addons/sale_line_quantity_properties_based/sale_order_line.py
odoo_addons/sale_line_quantity_properties_based/i18n/ar.po
odoo_addons/sale_line_quantity_properties_based/i18n/ca.po
odoo_addons/sale_line_quantity_properties_based/i18n/da.po
odoo_addons/sale_line_quantity_properties_based/i18n/de.po
odoo_addons/sale_line_quantity_properties_based/i18n/el_GR.po
odoo_addons/sale_line_quantity_properties_based/i18n/es.po
odoo_addons/sale_line_quantity_properties_based/i18n/es_ES.po
odoo_addons/sale_line_quantity_properties_based/i18n/es_VE.po
odoo_addons/sale_line_quantity_properties_based/i18n/fi.po
odoo_addons/sale_line_quantity_properties_based/i18n/fr.po
odoo_addons/sale_line_quantity_properties_based/i18n/fr_CA.po
odoo_addons/sale_line_quantity_properties_based/i18n/fr_CH.po
odoo_addons/sale_line_quantity_properties_based/i18n/fr_FR.po
odoo_addons/sale_line_quantity_properties_based/i18n/gl.po
odoo_addons/sale_line_quantity_properties_based/i18n/hr.po
odoo_addons/sale_line_quantity_properties_based/i18n/hr_HR.po
odoo_addons/sale_line_quantity_properties_based/i18n/it.po
odoo_addons/sale_line_quantity_properties_based/i18n/nb.po
odoo_addons/sale_line_quantity_properties_based/i18n/nb_NO.po
odoo_addons/sale_line_quantity_properties_based/i18n/nl.po
odoo_addons/sale_line_quantity_properties_based/i18n/nl_NL.po
odoo_addons/sale_line_quantity_properties_based/i18n/pt.po
odoo_addons/sale_line_quantity_properties_based/i18n/pt_BR.po
odoo_addons/sale_line_quantity_properties_based/i18n/pt_PT.po
odoo_addons/sale_line_quantity_properties_based/i18n/ro.po
odoo8_addon_sale_line_quantity_properties_based-8.0.1.0.0.99.dev18.dist-info/METADATA
odoo8_addon_sale_line_quantity_properties_based-8.0.1.0.0.99.dev18.dist-info/WHEEL
odoo8_addon_sale_line_quantity_properties_based-8.0.1.0.0.99.dev18.dist-info/namespace_packages.txt
odoo8_addon_sale_line_quantity_properties_based-8.0.1.0.0.99.dev18.dist-info/top_level.txt
odoo8_addon_sale_line_quantity_properties_based-8.0.1.0.0.99.dev18.dist-info/RECORD
